contop/__init__.py
contop/core.py
contop/optimisation.py
contop/reservoir_computing.py
contop/tests.py
contop-0.3.0.dist-info/licenses/LICENSE
contop-0.3.0.dist-info/METADATA
contop-0.3.0.dist-info/WHEEL
contop-0.3.0.dist-info/top_level.txt
contop-0.3.0.dist-info/RECORD
