Metadata-Version: 2.4
Name: contop
Version: 0.3.0
Summary: A library for analysing time series using Continuous Ordinal Patterns
Author-email: Massimiliano Zanin <massimiliano.zanin@gmail.com>
License-Expression: AGPL-3.0-only
Project-URL: Homepage, https://gitlab.com/MZanin/contop
Project-URL: Issues, https://gitlab.com/MZanin/contop/issues
Project-URL: Documentation, https://gitlab.com/MZanin/contop/-/wikis/home
Project-URL: Repository, https://gitlab.com/MZanin/contop
Project-URL: Changelog, https://gitlab.com/MZanin/contop/-/wikis/home/Version-History
Keywords: time series,ordinal patterns,continuous ordinal patterns,irreversibility,statistical physics
Classifier: Programming Language :: Python :: 3
Classifier: Operating System :: OS Independent
Requires-Python: >=3.11
License-File: LICENSE
Requires-Dist: numpy
Requires-Dist: statsmodels
Requires-Dist: scipy
Requires-Dist: numba
Requires-Dist: scikit-learn
Provides-Extra: test
Requires-Dist: pytest; extra == "test"
Requires-Dist: pytest-cov; extra == "test"
Requires-Dist: coverage; extra == "test"
Provides-Extra: all
Requires-Dist: contop[lint,test]; extra == "all"
Dynamic: license-file
